merry/__init__.py
merry-0.3.0.dist-info/LICENSE
merry-0.3.0.dist-info/METADATA
merry-0.3.0.dist-info/WHEEL
merry-0.3.0.dist-info/top_level.txt
merry-0.3.0.dist-info/RECORD
